pod_exec.py
pod_exec-0.0.2.dist-info/LICENSE
pod_exec-0.0.2.dist-info/METADATA
pod_exec-0.0.2.dist-info/WHEEL
pod_exec-0.0.2.dist-info/top_level.txt
pod_exec-0.0.2.dist-info/RECORD
