Metadata-Version: 2.1
Name: pod-exec
Version: 0.0.2
Summary: Command line controller help for executing command in a pod
Author: wangziling100
Author-email: wangziling100@163.com
Classifier: Programming Language :: Python :: 3
Classifier: License :: OSI Approved :: MIT License
License-File: LICENSE
